pybinary/__init__.py
pybinary/binary_types.py
pybinary/serializable.py
pybinary-0.9.6.dist-info/licenses/LICENSE
pybinary-0.9.6.dist-info/METADATA
pybinary-0.9.6.dist-info/WHEEL
pybinary-0.9.6.dist-info/top_level.txt
pybinary-0.9.6.dist-info/RECORD
