Metadata-Version: 2.4
Name: pybinary
Version: 0.9.6
Summary: Better binary serialization for python
Author-email: lim8en1 <lim8en1@proton.me>
Project-URL: Homepage, https://github.com/lim8en1/pybinary
Project-URL: Bug Tracker, https://github.com/lim8en1/pybinary/issues
Classifier: Programming Language :: Python :: 3
Classifier: License :: OSI Approved :: MIT License
Classifier: Operating System :: OS Independent
Requires-Python: >=3.10
License-File: LICENSE
Dynamic: license-file
